pyOnvotar/__init__.py
pyOnvotar/cli.py
pyOnvotar/pyOnvotar.py
pyOnvotar-0.1.1.dist-info/DESCRIPTION.rst
pyOnvotar-0.1.1.dist-info/METADATA
pyOnvotar-0.1.1.dist-info/RECORD
pyOnvotar-0.1.1.dist-info/WHEEL
pyOnvotar-0.1.1.dist-info/entry_points.txt
pyOnvotar-0.1.1.dist-info/metadata.json
pyOnvotar-0.1.1.dist-info/top_level.txt
