Metadata-Version: 2.0
Name: pyOnvotar
Version: 0.1.1
Summary: pyOnvotar wraps as a pypi installable lib all code for onVotar bots
Home-page: https://github.com/carlesm/pyOnvotar
Author: Carles Mateu
Author-email: carlesm@gmail.com
License: MIT license
Keywords: pyOnvotar
Platform: UNKNOWN
Classifier: Development Status :: 2 - Pre-Alpha
Classifier: Intended Audience :: Developers
Classifier: License :: OSI Approved :: MIT License
Classifier: Natural Language :: English
Classifier: Programming Language :: Python :: 2
Classifier: Programming Language :: Python :: 2.6
Classifier: Programming Language :: Python :: 2.7
Classifier: Programming Language :: Python :: 3
Classifier: Programming Language :: Python :: 3.3
Classifier: Programming Language :: Python :: 3.4
Classifier: Programming Language :: Python :: 3.5
Requires-Dist: Click (>=6.0)
